prefill_haalcentraalhr/__init__.py
prefill_haalcentraalhr/admin.py
prefill_haalcentraalhr/apps.py
prefill_haalcentraalhr/constants.py
prefill_haalcentraalhr/models.py
prefill_haalcentraalhr/plugin.py
prefill_haalcentraalhr/migrations/0001_initial.py
prefill_haalcentraalhr/migrations/__init__.py
prefill_haalcentraalhr/tests/__init__.py
prefill_haalcentraalhr/tests/test_plugin.py
prefill_haalcentraalhr-0.1.0.dist-info/LICENSE
prefill_haalcentraalhr-0.1.0.dist-info/METADATA
prefill_haalcentraalhr-0.1.0.dist-info/WHEEL
prefill_haalcentraalhr-0.1.0.dist-info/top_level.txt
prefill_haalcentraalhr-0.1.0.dist-info/RECORD
