Metadata-Version: 2.1
Name: prefill-haalcentraalhr
Version: 0.1.0
Summary: TODO
Home-page: https://github.com/open-formulieren/open-forms-ext-haalcentraal-hr
Author: Maykin Media
Author-email: support@maykinmedia.nl
License: MIT
Project-URL: Documentation, http://prefill_haalcentraalhr.readthedocs.io/en/latest/
Project-URL: Changelog, https://github.com/open-formulieren/open-forms-ext-haalcentraal-hr/blob/main/CHANGELOG.rst
Project-URL: Bug Tracker, https://github.com/open-formulieren/open-forms-ext-haalcentraal-hr/issues
Project-URL: Source Code, https://github.com/open-formulieren/open-forms-ext-haalcentraal-hr
Keywords: TODO
Classifier: Development Status :: 3 - Alpha
Classifier: Framework :: Django
Classifier: Framework :: Django :: 3.2
Classifier: Intended Audience :: Developers
Classifier: Operating System :: Unix
Classifier: Operating System :: MacOS
Classifier: Operating System :: Microsoft :: Windows
Classifier: Programming Language :: Python :: 3.8
Classifier: Programming Language :: Python :: 3.9
Classifier: Programming Language :: Python :: 3.10
Classifier: Topic :: Software Development :: Libraries :: Python Modules
License-File: LICENSE
Requires-Dist: django >=3.2
Requires-Dist: zgw-consumers
Provides-Extra: docs
Requires-Dist: sphinx ; extra == 'docs'
Requires-Dist: sphinx-rtd-theme ; extra == 'docs'
Provides-Extra: pep8
Requires-Dist: flake8 ; extra == 'pep8'
Provides-Extra: release
Requires-Dist: bumpversion ; extra == 'release'
Requires-Dist: twine ; extra == 'release'
Provides-Extra: tests
Requires-Dist: pytest ; extra == 'tests'
Requires-Dist: pytest-django ; extra == 'tests'
Requires-Dist: tox ; extra == 'tests'
Requires-Dist: isort ; extra == 'tests'
Requires-Dist: black ; extra == 'tests'
Requires-Dist: flake8 ; extra == 'tests'
Requires-Dist: coverage ; extra == 'tests'
